battery_notify/__init__.py
battery_notify/__metadata__.py
battery_notify/configs.py
battery_notify/daemon.py
battery_notify/notify.py
battery_notify/usage.py
battery_notify/utils.py
battery_notify/bin/__init__.py
battery_notify/bin/battery_daemon.py
battery_notify/bin/battery_notify.py
battery_notify-1.4.dist-info/entry_points.txt
battery_notify-1.4.dist-info/WHEEL
battery_notify-1.4.dist-info/METADATA
battery_notify-1.4.dist-info/RECORD
