Metadata-Version: 2.1
Name: battery-notify
Version: 1.4
Summary: Battery notification applet for informing about battery status.
Keywords: dbus,notify,battery,desktop,status
Author-email: Dimitris Zlatanidis <dslackw@gmail.com>
Maintainer-email: Dimitris Zlatanidis <dslackw@gmail.com>
Requires-Python: >=3.9
Classifier: Development Status :: 5 - Production/Stable
Classifier: License :: OSI Approved :: GNU General Public License v3 or later (GPLv3+)
Classifier: Operating System :: POSIX :: Linux
Classifier: Programming Language :: Python :: 3.9
Classifier: Topic :: Desktop Environment
Classifier: Topic :: System :: Monitoring
Classifier: Topic :: System :: Hardware
Requires-Dist: python-daemon>=3.0.1
Requires-Dist: tomli>=1.2.2
Requires-Dist: psutil>=5.9.7
Requires-Dist: notify2>=0.3.1
Project-URL: Changelog, https://gitlab.com/dslackw/battery-notify/-/blob/main/CHANGELOG.md
Project-URL: Documentation, https://gitlab.com/dslackw/battery-notify/
Project-URL: Homepage, https://gitlab.com/dslackw/battery-notify/
Project-URL: Repository, https://gitlab.com/dslackw/battery-notify.git
